{
  "connections": [
    {
      "id": 1,
      "name": "Iosue Margareta",
      "avatarId": 10,
      "email": "iosue00@connect.com"
    },
    {
      "id": 2,
      "name": "Urban Kristine",
      "avatarId": 20,
      "email": "kristine@connect.com"
    },
    {
      "id": 3,
      "name": "Damjana Adhiambo",
      "avatarId": 30,
      "email": "adhiambo@connect.com"
    },
    {
      "id": 4,
      "name": "aaaa",
      "avatarId": 40,
      "email": "aaa@connect.com"
    },
    {
      "id": 5,
      "name": "bbbb",
      "avatarId": 50,
      "email": "bbbb@connect.com"
    }
  ]
}
